LICENSE
MANIFEST.in
README.rst
setup.py
conf/org.gnome.githubrepositories.search.conf
conf/org.gnome.githubrepositories.search.gschema.xml
conf/org.gnome.githubrepositories.search.ini
conf/org.gnome.githubrepositories.search.service
data/popup.glade
gnome_shell_search_github_repositories.egg-info/PKG-INFO
gnome_shell_search_github_repositories.egg-info/SOURCES.txt
gnome_shell_search_github_repositories.egg-info/dependency_links.txt
gnome_shell_search_github_repositories.egg-info/entry_points.txt
gnome_shell_search_github_repositories.egg-info/not-zip-safe
gnome_shell_search_github_repositories.egg-info/requires.txt
gnome_shell_search_github_repositories.egg-info/top_level.txt
gs_search_github_repositories/__init__.py
gs_search_github_repositories/daemon.py
gs_search_github_repositories/githubutils.py
gs_search_github_repositories/popup.py