Metadata-Version: 1.0
Name: gnome-shell-search-github-repositories
Version: 1.0.1
Summary: A gnome shell search provider for your github repos
Home-page: http://github.com/ralphbean/gnome-shell-search-github-repositories
Author: Ralph Bean
Author-email: rbean@redhat.com
License: GPLv3
Platform: UNKNOWN
